<?xml version="1.0" encoding="UTF-8" standalone="yes"?>
<persistence version="2.0"
             xsi:schemaLocation="http://java.sun.com/xml/ns/persistence http://java.sun.com/xml/ns/persistence/persistence_2_0.xsd"
             xmlns="http://java.sun.com/xml/ns/persistence"
             xmlns:xsi="http://www.w3.org/2001/XMLSchema-instance">
    <persistence-unit name="org.collectionspace.services.authorization">
        <class>org.collectionspace.services.authorization.perms.Permission</class>
        <class>org.collectionspace.services.authorization.perms.PermissionAction</class>
        <class>org.collectionspace.services.authorization.PermissionRoleRel</class>
        <class>org.collectionspace.services.authorization.Role</class>
        <class>org.collectionspace.services.authorization.AccountRoleRel</class>
        <properties>
            <property name="javax.persistence.jdbc.driver" value="org.postgresql.Driver" />
            <property name="javax.persistence.jdbc.url" value="@DB_CSPACE_URL@" />
            <property name="javax.persistence.jdbc.user" value="@DB_CSPACE_USER@" />
            <property name="javax.persistence.jdbc.password" value="@DB_CSPACE_PASSWORD@" />
            <property name="hibernate.show_sql" value="true" />
            <!-- Disable XML Mapping so that javax.xml.bind classes do not attempt to be loaded -->
            <property name="hibernate.xml_mapping_enabled" value="false" />
        </properties>
    </persistence-unit>
</persistence>
